{
  "group": "oneweb",
  "learned_utc": "2026-07-22T19:16:26.647939+00:00",
  "pct": 99.0,
  "min_km": 5.0,
  "orbital_regime": "LEO",
  "snapshots": [
    "2026-07-22/0200Z",
    "2026-07-22/0750Z",
    "2026-07-22/0800Z",
    "2026-07-22/1400Z"
  ],
  "regimes": {
    "station": [
      {
        "lo": 6,
        "hi": 12,
        "n": 79,
        "cut_km": 1.9965017615197194,
        "basis": "bin"
      },
      {
        "lo": 12,
        "hi": 24,
        "n": 1513,
        "cut_km": 4.875282544037972,
        "basis": "bin"
      },
      {
        "lo": 24,
        "hi": 48,
        "n": 1012,
        "cut_km": 33.334387310705715,
        "basis": "bin"
      }
    ],
    "falling": []
  }
}