{
  "group": "starlink",
  "learned_utc": "2026-07-22T08:29:10.032279+00:00",
  "pct": 99.0,
  "min_km": 5.0,
  "snapshots": [
    "2026-07-22/0200Z",
    "2026-07-22/0750Z",
    "2026-07-22/0800Z"
  ],
  "regimes": {
    "station": [
      {
        "lo": 6,
        "hi": 12,
        "n": 1524,
        "cut_km": 22.62453704607919,
        "basis": "bin"
      },
      {
        "lo": 12,
        "hi": 24,
        "n": 17397,
        "cut_km": 43.917942491732234,
        "basis": "bin"
      },
      {
        "lo": 24,
        "hi": 48,
        "n": 9952,
        "cut_km": 51.380549121355386,
        "basis": "bin"
      },
      {
        "lo": 48,
        "hi": 96,
        "n": 346,
        "cut_km": 77.40441281782324,
        "basis": "bin"
      },
      {
        "lo": 96,
        "hi": 1000000000.0,
        "n": 3,
        "cut_km": 49.77839498184772,
        "basis": "regime"
      }
    ],
    "falling": [
      {
        "lo": 3,
        "hi": 6,
        "n": 2,
        "cut_km": 282.5476811392162,
        "basis": "regime"
      },
      {
        "lo": 6,
        "hi": 12,
        "n": 566,
        "cut_km": 70.70699925528825,
        "basis": "bin"
      },
      {
        "lo": 12,
        "hi": 24,
        "n": 1904,
        "cut_km": 282.8392160122426,
        "basis": "bin"
      },
      {
        "lo": 24,
        "hi": 48,
        "n": 518,
        "cut_km": 304.17083430773425,
        "basis": "bin"
      },
      {
        "lo": 48,
        "hi": 96,
        "n": 8,
        "cut_km": 282.5476811392162,
        "basis": "regime"
      }
    ]
  }
}